findmy/__init__.py
home_assistant_findmy-1.1.0.dist-info/LICENSE.md
home_assistant_findmy-1.1.0.dist-info/METADATA
home_assistant_findmy-1.1.0.dist-info/WHEEL
home_assistant_findmy-1.1.0.dist-info/entry_points.txt
home_assistant_findmy-1.1.0.dist-info/top_level.txt
home_assistant_findmy-1.1.0.dist-info/RECORD
