Metadata-Version: 2.1
Name: home-assistant-findmy
Version: 1.1.0
Summary: A python script that reads local FindMy cache files to broadcast device locations (including those of AirTags, AirPods, Apple Watches, iPhones) to Home Assistant via MQTT.
Home-page: https://github.com/muehlt/home-assistant-findmy
Author: muehlt
Author-email: thomas@savory.at
Classifier: Programming Language :: Python :: 3
Requires-Python: >=3.6
License-File: LICENSE.md
Requires-Dist: python-dotenv ==0.21.0
Requires-Dist: Unidecode ==1.3.6
Requires-Dist: click ~=8.1.6
Requires-Dist: paho-mqtt ~=1.6.1
Requires-Dist: rich ~=13.5.2
